{
  "ETBbcnfnqsBF": {
    "name": "Stop AI Engine",
    "type": "Function",
    "value": "stop_ai_engine"
  },
  "uiFhNKWoJeLN": {
    "name": "Pause AI Engine",
    "type": "Function",
    "value": "pause_ai_engine"
  },
  "EhcJSMEYPfML": {
    "name": "Open CMD",
    "type": "Command",
    "value": "cmd"
  },
  "ZqhdxtnXFmlI": {
    "name": "Close Window",
    "type": "Hotkey",
    "value": "Alt+F4"
  },
  "LaQzvAqKvrwE": {
    "name": "Arrow Left",
    "type": "Hotkey",
    "value": "Left"
  },
  "nHbxNdUIZHNe": {
    "name": "Arrow Right",
    "type": "Hotkey",
    "value": "Right"
  },
  "sFyfDTyhZARz": {
    "name": "Arrow Up",
    "type": "Hotkey",
    "value": "Up"
  },
  "clUnLPiRAoTp": {
    "name": "Arrow Down",
    "type": "Hotkey",
    "value": "Down"
  }
}